simpleaicv/__init__.py
simpleaicv/imageloc.py
simpleaicv/speak.py
simpleaicv-0.0.1.dist-info/LICENCE
simpleaicv-0.0.1.dist-info/METADATA
simpleaicv-0.0.1.dist-info/WHEEL
simpleaicv-0.0.1.dist-info/top_level.txt
simpleaicv-0.0.1.dist-info/RECORD
